CHANGES.txt
LICENSE.txt
MANIFEST.in
README.rst
setup.py
docs/Makefile
docs/conf.py
docs/future-development.rst
docs/index.rst
docs/intro.rst
docs/make.bat
docs/rtd-requirements.txt
docs/_build/.DS_Store
docs/_build/doctrees/environment.pickle
docs/_build/doctrees/future-development.doctree
docs/_build/doctrees/index.doctree
docs/_build/doctrees/intro.doctree
docs/_build/doctrees/api/create-view.doctree
docs/_build/doctrees/api/delete-view.doctree
docs/_build/doctrees/api/detail-view.doctree
docs/_build/doctrees/api/form-view.doctree
docs/_build/doctrees/api/index.doctree
docs/_build/doctrees/api/list-view.doctree
docs/_build/doctrees/api/redirect-view.doctree
docs/_build/doctrees/api/template-view.doctree
docs/_build/doctrees/api/update-view.doctree
docs/_build/doctrees/api/view.doctree
docs/_build/html/.buildinfo
docs/_build/html/future-development.html
docs/_build/html/genindex.html
docs/_build/html/index.html
docs/_build/html/intro.html
docs/_build/html/objects.inv
docs/_build/html/py-modindex.html
docs/_build/html/search.html
docs/_build/html/searchindex.js
docs/_build/html/_sources/future-development.txt
docs/_build/html/_sources/index.txt
docs/_build/html/_sources/intro.txt
docs/_build/html/_sources/api/create-view.txt
docs/_build/html/_sources/api/delete-view.txt
docs/_build/html/_sources/api/detail-view.txt
docs/_build/html/_sources/api/form-view.txt
docs/_build/html/_sources/api/index.txt
docs/_build/html/_sources/api/list-view.txt
docs/_build/html/_sources/api/redirect-view.txt
docs/_build/html/_sources/api/template-view.txt
docs/_build/html/_sources/api/update-view.txt
docs/_build/html/_sources/api/view.txt
docs/_build/html/_static/ajax-loader.gif
docs/_build/html/_static/basic.css
docs/_build/html/_static/comment-bright.png
docs/_build/html/_static/comment-close.png
docs/_build/html/_static/comment.png
docs/_build/html/_static/doctools.js
docs/_build/html/_static/down-pressed.png
docs/_build/html/_static/down.png
docs/_build/html/_static/file.png
pyramid_views.egg-info/PKG-INFO
pyramid_views.egg-info/SOURCES.txt
pyramid_views.egg-info/dependency_links.txt
pyramid_views.egg-info/requires.txt
pyramid_views.egg-info/top_level.txt
