Metadata-Version: 1.0
Name: pyramid-views
Version: 1.0.1
Summary: UNKNOWN
Home-page: https://github.com/nomadicfm/pyramid-views
Author: Adam Charnock
Author-email: adam@adamcharnock.com
License: MIT
Platform: UNKNOWN
